Workbook
Name Slicer_gender: #N/A

Sheet Data_set 
A1: gender | B1: age | C1: Investment_Avenues | D1: Mutual_Funds | E1: Equity_Market | F1: Debentures | G1: Government_Bonds | H1: Fixed_Deposits | I1: PPF | J1: Gold | K1: Stock_Marktet | L1: Factor | M1: Objective | N1: Purpose | O1: Duration | P1: Invest_Monitor | Q1: Expect | R1: Avenue | S1: What are your savings objectives? | T1: Reason_Equity | U1: Reason_Mutual | V1: Reason_Bonds | W1: Reason_FD | X1: Source
A2: Female | B2: 34 | C2: Yes | D2: 1 | E2: 2 | F2: 5 | G2: 3 | H2: 7 | I2: 6 | J2: 4 | K2: Yes | L2: Returns | M2: Capital Appreciation | N2: Wealth Creation | O2: 1-3 years | P2: Monthly | Q2: 20%-30% | R2: Mutual Fund | S2: Retirement Plan | T2: Capital Appreciation | U2: Better Returns | V2: Safe Investment | W2: Fixed Returns | X2: Newspapers and Magazines
A3: Female | B3: 23 | C3: Yes | D3: 4 | E3: 3 | F3: 2 | G3: 1 | H3: 5 | I3: 6 | J3: 7 | K3: No | L3: Locking Period | M3: Capital Appreciation | N3: Wealth Creation | O3: More than 5 years | P3: Weekly | Q3: 20%-30% | R3: Mutual Fund | S3: Health Care | T3: Dividend | U3: Better Returns | V3: Safe Investment | W3: High Interest Rates | X3: Financial Consultants
A4: Male | B4: 30 | C4: Yes | D4: 3 | E4: 6 | F4: 4 | G4: 2 | H4: 5 | I4: 1 | J4: 7 | K4: Yes | L4: Returns | M4: Capital Appreciation | N4: Wealth Creation | O4: 3-5 years | P4: Daily | Q4: 20%-30% | R4: Equity | S4: Retirement Plan | T4: Capital Appreciation | U4: Tax Benefits | V4: Assured Returns | W4: Fixed Returns | X4: Television
A5: Male | B5: 22 | C5: Yes | D5: 2 | E5: 1 | F5: 3 | G5: 7 | H5: 6 | I5: 4 | J5: 5 | K5: Yes | L5: Returns | M5: Income | N5: Wealth Creation | O5: Less than 1 year | P5: Daily | Q5: 10%-20% | R5: Equity | S5: Retirement Plan | T5: Dividend | U5: Fund Diversification | V5: Tax Incentives | W5: High Interest Rates | X5: Internet
A6: Female | B6: 24 | C6: No | D6: 2 | E6: 1 | F6: 3 | G6: 6 | H6: 4 | I6: 5 | J6: 7 | K6: No | L6: Returns | M6: Income | N6: Wealth Creation | O6: Less than 1 year | P6: Daily | Q6: 20%-30% | R6: Equity | S6: Retirement Plan | T6: Capital Appreciation | U6: Better Returns | V6: Safe Investment | W6: Risk Free | X6: Internet
A7: Female | B7: 24 | C7: No | D7: 7 | E7: 5 | F7: 4 | G7: 6 | H7: 3 | I7: 1 | J7: 2 | K7: No | L7: Risk | M7: Capital Appreciation | N7: Wealth Creation | O7: 1-3 years | P7: Daily | Q7: 30%-40% | R7: Mutual Fund | S7: Retirement Plan | T7: Liquidity | U7: Fund Diversification | V7: Safe Investment | W7: Risk Free | X7: Internet
A8: Female | B8: 27 | C8: Yes | D8: 3 | E8: 6 | F8: 4 | G8: 2 | H8: 5 | I8: 1 | J8: 7 | K8: Yes | L8: Returns | M8: Capital Appreciation | N8: Wealth Creation | O8: 3-5 years | P8: Monthly | Q8: 20%-30% | R8: Equity | S8: Retirement Plan | T8: Capital Appreciation | U8: Better Returns | V8: Assured Returns | W8: High Interest Rates | X8: Financial Consultants
A9: Male | B9: 21 | C9: Yes | D9: 2 | E9: 3 | F9: 7 | G9: 4 | H9: 6 | I9: 1 | J9: 5 | K9: Yes | L9: Risk | M9: Capital Appreciation | N9: Wealth Creation | O9: 3-5 years | P9: Monthly | Q9: 20%-30% | R9: Mutual Fund | S9: Retirement Plan | T9: Capital Appreciation | U9: Better Returns | V9: Assured Returns | W9: Risk Free | X9: Newspapers and Magazines
A10: Male | B10: 35 | C10: Yes | D10: 2 | E10: 4 | F10: 7 | G10: 5 | H10: 3 | I10: 1 | J10: 6 | K10: Yes | L10: Returns | M10: Growth | N10: Savings for Future | O10: 1-3 years | P10: Weekly | Q10: 20%-30% | R10: Equity | S10: Retirement Plan | T10: Capital Appreciation | U10: Fund Diversification | V10: Safe Investment | W10: Fixed Returns | X10: Television
A11: Male | B11: 31 | C11: Yes | D11: 1 | E11: 3 | F11: 7 | G11: 4 | H11: 5 | I11: 2 | J11: 6 | K11: Yes | L11: Returns | M11: Capital Appreciation | N11: Wealth Creation | O11: 3-5 years | P11: Monthly | Q11: 30%-40% | R11: Fixed Deposits | S11: Retirement Plan | T11: Capital Appreciation | U11: Fund Diversification | V11: Assured Returns | W11: Fixed Returns | X11: Newspapers and Magazines
A12: Female | B12: 35 | C12: Yes | D12: 2 | E12: 4 | F12: 7 | G12: 5 | H12: 3 | I12: 1 | J12: 6 | K12: Yes | L12: Risk | M12: Growth | N12: Savings for Future | O12: 3-5 years | P12: Monthly | Q12: 20%-30% | R12: Mutual Fund | S12: Retirement Plan | T12: Capital Appreciation | U12: Better Returns | V12: Assured Returns | W12: Risk Free | X12: Financial Consultants
A13: Male | B13: 29 | C13: Yes | D13: 2 | E13: 5 | F13: 7 | G13: 6 | H13: 3 | I13: 1 | J13: 4 | K13: Yes | L13: Risk | M13: Capital Appreciation | N13: Wealth Creation | O13: 1-3 years | P13: Monthly | Q13: 20%-30% | R13: Mutual Fund | S13: Retirement Plan | T13: Capital Appreciation | U13: Fund Diversification | V13: Assured Returns | W13: Fixed Returns | X13: Financial Consultants
... A41: Male | B41: 29 | C41: Yes | D41: 4 | E41: 3 | F41: 5 | G41: 7 | H41: 2 | I41: 1 | J41: 6 | K41: Yes | L41: Returns | M41: Capital Appreciation | N41: Wealth Creation | O41: 3-5 years | P41: Monthly | Q41: 20%-30% | R41: Fixed Deposits | S41: Retirement Plan | T41: Dividend | U41: Better Returns | V41: Safe Investment | W41: Fixed Returns | X41: Financial Consultants

Sheet Task 1
A1: Gender | B1: Count
A2: Male | B2: =COUNTIF('Data_set '!$A:$A,"Male") -> 25
A3: Female | B3: =COUNTIF('Data_set '!$A:$A,"Female") -> 15
A4: Total | B4: =SUM(B2:B3) -> 40

Sheet Task 2
A1: Chart 1 - Distribution of Participants Across Investment Avenues
A3: AVENUE | B3: COUNT
A5: Mutual Fund | B5: =COUNTIF('Data_set '!$R:$R,"Mutual Fund") -> 18
A6: Equity | B6: =COUNTIF('Data_set '!$R:$R,"Equity") -> 10
A7: Fixed deposit | B7: =COUNTIF('Data_set '!$R:$R,"Fixed Deposits") -> 9
A8: Public Provident Fund | B8: =COUNTIF('Data_set '!$R:$R,"Public Provident Fund") -> 3
A27: Chart 2 - Reasons Behind Investment Choices
A29: REASON | B29: COUNT
A30: Capital Appreciation | B30: =COUNTIF('Data_set '!$T:$T,"Capital Appreciation") -> 30
A31: Better Returns | B31: =COUNTIF('Data_set '!$U:$U,"Better Returns") -> 24
A32: Safe Investment | B32: =COUNTIF('Data_set '!$V:$V,"Safe Investment") -> 13
A33: Fixed Returns | B33: =COUNTIF('Data_set '!$W:$W,"Fixed Returns") -> 18
A34: Dividend | B34: =COUNTIF('Data_set '!T:T,"Dividend") -> 8
A35: Tax Benefits | B35: =COUNTIF('Data_set '!U:U,"Tax Benefits") -> 3

Sheet Task 3
A1: Chart 1 - Savings Objectives
A3: Saving Objective | B3: Counts
A4: Retirement Plans | B4: =COUNTIF('Data_set '!$S:$S,"Retirement Plan") -> 24
A5: Health Care | B5: =COUNTIF('Data_set '!$S:$S,"Health Care") -> 13
A6: Education | B6: =COUNTIF('Data_set '!$S:$S,"Education") -> 3
A30: Chart 2 - Information Sources
A32: Source | B32: Count
A33: Financial Consultants | B33: =COUNTIF('Data_set '!$X:$X, "Financial Consultants") -> 16
A34: Newspapers and Magazines | B34: =COUNTIF('Data_set '!$X:$X,"Newspapers and Magazines") -> 14
A35: Television | B35: =COUNTIF('Data_set '!$X:$X,"Television") -> 6
A36: Internet | B36: =COUNTIF('Data_set '!$X:$X,"Internet") -> 4

Sheet Task 4
A1: Chart 1 - Investment Duration
A3: Duration | B3: Counts
A4: Less than 1 year | B4: =COUNTIF('Data_set '!$O:$O,"Less than 1 year") -> 2
A5: 1-3 years | B5: =COUNTIF('Data_set '!$O:$O,"1-3 years") -> 18
A6: 3-5 years | B6: =COUNTIF('Data_set '!$O:$O,"3-5 years") -> 19
A7: More than 5 years | B7: =COUNTIF('Data_set '!$O:$O,"More than 5 years") -> 1
A29: Chart 2 - Expectation
A31: Expectation | B31: Count
A32: 10%-20% | B32: =COUNTIF('Data_set '!$Q:$Q,"10%-20%") -> 3
A33: 20%-30% | B33: =COUNTIF('Data_set '!$Q:$Q,"20%-30%") -> 32
A34: 30%-40% | B34: =COUNTIF('Data_set '!$Q:$Q,"30%-40%") -> 5

Sheet Task 5
A1: Chart 1: Correlation between age and expected returns
A3: Age | B3: Expectation | C3: Midpoint
A4: ='Data_set '!$B2 -> 34 | B4: ='Data_set '!Q2 -> 20%-30% | C4: =IF(B4="10%-20%",15,IF(B4="20%-30%",25,IF(B4="30%-40%",35,0))) -> 25
A5: ='Data_set '!$B3 -> 23 | B5: ='Data_set '!Q3 -> 20%-30% | C5: =IF(B5="10%-20%",15,IF(B5="20%-30%",25,IF(B5="30%-40%",35,0))) -> 25
A6: ='Data_set '!$B4 -> 30 | B6: ='Data_set '!Q4 -> 20%-30% | C6: =IF(B6="10%-20%",15,IF(B6="20%-30%",25,IF(B6="30%-40%",35,0))) -> 25
A7: ='Data_set '!$B5 -> 22 | B7: ='Data_set '!Q5 -> 10%-20% | C7: =IF(B7="10%-20%",15,IF(B7="20%-30%",25,IF(B7="30%-40%",35,0))) -> 15
A8: ='Data_set '!$B6 -> 24 | B8: ='Data_set '!Q6 -> 20%-30% | C8: =IF(B8="10%-20%",15,IF(B8="20%-30%",25,IF(B8="30%-40%",35,0))) -> 25
A9: ='Data_set '!$B7 -> 24 | B9: ='Data_set '!Q7 -> 30%-40% | C9: =IF(B9="10%-20%",15,IF(B9="20%-30%",25,IF(B9="30%-40%",35,0))) -> 35
A10: ='Data_set '!$B8 -> 27 | B10: ='Data_set '!Q8 -> 20%-30% | C10: =IF(B10="10%-20%",15,IF(B10="20%-30%",25,IF(B10="30%-40%",35,0))) -> 25
A11: ='Data_set '!$B9 -> 21 | B11: ='Data_set '!Q9 -> 20%-30% | C11: =IF(B11="10%-20%",15,IF(B11="20%-30%",25,IF(B11="30%-40%",35,0))) -> 25
A12: ='Data_set '!$B10 -> 35 | B12: ='Data_set '!Q10 -> 20%-30% | C12: =IF(B12="10%-20%",15,IF(B12="20%-30%",25,IF(B12="30%-40%",35,0))) -> 25
A13: ='Data_set '!$B11 -> 31 | B13: ='Data_set '!Q11 -> 30%-40% | C13: =IF(B13="10%-20%",15,IF(B13="20%-30%",25,IF(B13="30%-40%",35,0))) -> 35
A14: ='Data_set '!$B12 -> 35 | B14: ='Data_set '!Q12 -> 20%-30% | C14: =IF(B14="10%-20%",15,IF(B14="20%-30%",25,IF(B14="30%-40%",35,0))) -> 25
A15: ='Data_set '!$B13 -> 29 | B15: ='Data_set '!Q13 -> 20%-30% | C15: =IF(B15="10%-20%",15,IF(B15="20%-30%",25,IF(B15="30%-40%",35,0))) -> 25
... A43: ='Data_set '!$B41 -> 29 | B43: ='Data_set '!Q41 -> 20%-30% | C43: =IF(B43="10%-20%",15,IF(B43="20%-30%",25,IF(B43="30%-40%",35,0))) -> 25
A46: Chart 2 :
A48: Duration | B48: Expectation | C48: Count
A49: 1 | B49: 25 | C49: =COUNTIF('Data_set '!O:O,"Less than 1 year") -> 2
A50: 2 | B50: 25 | C50: =COUNTIF('Data_set '!O:O,"1-3 years") -> 18
A51: 3 | B51: 25 | C51: =COUNTIF('Data_set '!O:O,"3-5 years") -> 19
A52: 4 | B52: 35 | C52: =COUNTIF('Data_set '!O:O,"More than 5 years") -> 1

Sheet Task 6 (Dashboard)
A1: INVESTMENT BEHAVIOR ANALYSIS DASHBOARD
